StrictMeta/__init__.py
StrictMeta/strict_meta.py
strictmeta-0.1.1.dist-info/licenses/lgpl-3.0.md
strictmeta-0.1.1.dist-info/METADATA
strictmeta-0.1.1.dist-info/WHEEL
strictmeta-0.1.1.dist-info/top_level.txt
strictmeta-0.1.1.dist-info/RECORD
