Metadata-Version: 2.4
Name: StrictMeta
Version: 0.1.1
Summary: A metaclass to enforce strict type checking and metadata handling for classes.
Author-email: Karsten Merkle <StrictMeta@karsten-merkle.de>
License-Expression: LGPL-3.0-only
Project-URL: Homepage, https://github.com/Karsten-Merkle/StrictMeta
Classifier: Development Status :: 1 - Planning
Classifier: Intended Audience :: Developers
Classifier: Programming Language :: Python :: 3
Classifier: Programming Language :: Python :: 3.13
Classifier: Topic :: Software Development :: Libraries :: Python Modules
Requires-Python: >=3.9
License-File: lgpl-3.0.md
Dynamic: license-file
